resqpy/__init__.py
resqpy/crs.py
resqpy/derived_model/__init__.py
resqpy/derived_model/_add_edges_per_column_property_array.py
resqpy/derived_model/_add_faults.py
resqpy/derived_model/_add_one_blocked_well_property.py
resqpy/derived_model/_add_one_grid_property_array.py
resqpy/derived_model/_add_single_cell_grid.py
resqpy/derived_model/_add_wells_from_ascii_file.py
resqpy/derived_model/_add_zone_by_layer_property.py
resqpy/derived_model/_coarsened_grid.py
resqpy/derived_model/_common.py
resqpy/derived_model/_copy_grid.py
resqpy/derived_model/_drape_to_surface.py
resqpy/derived_model/_extract_box.py
resqpy/derived_model/_extract_box_for_well.py
resqpy/derived_model/_fault_throw_scaling.py
resqpy/derived_model/_gather_ensemble.py
resqpy/derived_model/_interpolated_grid.py
resqpy/derived_model/_local_depth_adjustment.py
resqpy/derived_model/_refined_grid.py
resqpy/derived_model/_tilted_grid.py
resqpy/derived_model/_unsplit_grid.py
resqpy/derived_model/_zonal_grid.py
resqpy/derived_model/_zone_layer_ranges_from_array.py
resqpy/fault/__init__.py
resqpy/fault/_gcs_functions.py
resqpy/fault/_grid_connection_set.py
resqpy/grid/__init__.py
resqpy/grid/_cell_properties.py
resqpy/grid/_connection_sets.py
resqpy/grid/_create_grid_xml.py
resqpy/grid/_defined_geometry.py
resqpy/grid/_extract_functions.py
resqpy/grid/_face_functions.py
resqpy/grid/_faults.py
resqpy/grid/_grid.py
resqpy/grid/_grid_types.py
resqpy/grid/_intervals_info.py
resqpy/grid/_pillars.py
resqpy/grid/_pixel_maps.py
resqpy/grid/_points_functions.py
resqpy/grid/_regular_grid.py
resqpy/grid/_transmissibility.py
resqpy/grid/_write_hdf5_from_caches.py
resqpy/grid/_write_nexus_corp.py
resqpy/grid/_xyz.py
resqpy/grid_surface/__init__.py
resqpy/grid_surface/_blocked_well_populate.py
resqpy/grid_surface/_find_faces.py
resqpy/grid_surface/_grid_skin.py
resqpy/grid_surface/_grid_surface.py
resqpy/grid_surface/_trajectory_intersects.py
resqpy/grid_surface/grid_surface_cuda.py
resqpy/lines/__init__.py
resqpy-5.1.13.dist-info/METADATA
resqpy-5.1.13.dist-info/WHEEL
resqpy-5.1.13.dist-info/licenses/LICENSE
resqpy-5.1.13.dist-info/RECORD
