Metadata-Version: 2.4
Name: resqpy
Version: 5.1.13
Summary: Python API for working with RESQML models
License: MIT
License-File: LICENSE
Keywords: RESQML
Author: BP
Requires-Python: >=3.9,<3.13
Classifier: Development Status :: 5 - Production/Stable
Classifier: License :: OSI Approved :: MIT License
Classifier: Operating System :: OS Independent
Classifier: Programming Language :: Python :: 3
Classifier: Programming Language :: Python :: 3.9
Classifier: Programming Language :: Python :: 3.10
Classifier: Programming Language :: Python :: 3.11
Classifier: Programming Language :: Python :: 3.12
Classifier: Topic :: Scientific/Engineering
Classifier: Topic :: Scientific/Engineering :: Information Analysis
Classifier: Topic :: System :: Filesystems
Requires-Dist: h5py (>=3.7,<4.0)
Requires-Dist: joblib (>=1.2,<2.0)
Requires-Dist: lasio (>=0.31,<0.32)
Requires-Dist: lxml (>=5.1,<6.0)
Requires-Dist: numba (>=0.59,<1.0)
Requires-Dist: numpy (>=1.26,<2.0)
Requires-Dist: pandas (>=2.2,<3.0)
Requires-Dist: scipy (>=1.9,<2.0)
Project-URL: Documentation, https://resqpy.readthedocs.io/en/latest/
Project-URL: Repository, https://github.com/bp/resqpy
